p_js/__init__.py
p_js/p_js.py
p_js_rs-0.0.1.dist-info/METADATA
p_js_rs-0.0.1.dist-info/WHEEL
p_js_rs-0.0.1.dist-info/entry_points.txt
p_js_rs-0.0.1.dist-info/top_level.txt
p_js_rs-0.0.1.dist-info/RECORD
