Metadata-Version: 2.1
Name: p_js_rs
Version: 0.0.1
Summary: A package for working with JSON files
Author: Rajveer Singh
Author-email: Rajveer Singh <rajveersingh81248@gmail.com>
Classifier: Programming Language :: Python :: 3
Classifier: License :: OSI Approved :: MIT License
Classifier: Operating System :: OS Independent
Requires-Python: >=3.7
